dir_assistant/__init__.py
dir_assistant/__main__.py
dir_assistant/main.py
dir_assistant/assistant/__init__.py
dir_assistant/assistant/base_assistant.py
dir_assistant/assistant/base_embed.py
dir_assistant/assistant/cache_manager.py
dir_assistant/assistant/cgrag_assistant.py
dir_assistant/assistant/file_watcher.py
dir_assistant/assistant/git_assistant.py
dir_assistant/assistant/index.py
dir_assistant/assistant/lite_llm_assistant.py
dir_assistant/assistant/lite_llm_embed.py
dir_assistant/assistant/llama_cpp_assistant.py
dir_assistant/assistant/llama_cpp_embed.py
dir_assistant/assistant/rag_optimizer.py
dir_assistant/cli/__init__.py
dir_assistant/cli/config.py
dir_assistant/cli/models.py
dir_assistant/cli/platform_setup.py
dir_assistant/cli/setkey.py
dir_assistant/cli/start.py
dir_assistant-1.9.1.dist-info/licenses/LICENSE
test/__init__.py
test/test_git_assistant.py
test/test_smoketest_api_interactive.py
test/test_smoketest_api_noninteractive.py
test/test_smoketest_local_noninteractive.py
test/utils.py
dir_assistant-1.9.1.dist-info/METADATA
dir_assistant-1.9.1.dist-info/WHEEL
dir_assistant-1.9.1.dist-info/entry_points.txt
dir_assistant-1.9.1.dist-info/top_level.txt
dir_assistant-1.9.1.dist-info/RECORD
