Metadata-Version: 2.4
Name: dir-assistant
Version: 1.9.1
Summary: Chat with your current directory's files using a local or API LLM.
Home-page: https://github.com/curvedinf/dir-assistant
Author: Chase Adams
Author-email: chase.adams@gmail.com
License: MIT
Classifier: Programming Language :: Python :: 3
Classifier: License :: OSI Approved :: MIT License
Classifier: Operating System :: OS Independent
Requires-Python: >=3.6
License-File: LICENSE
Requires-Dist: faiss-cpu
Requires-Dist: litellm
Requires-Dist: colorama
Requires-Dist: sqlitedict
Requires-Dist: prompt-toolkit
Requires-Dist: watchdog
Requires-Dist: google-generativeai
Requires-Dist: openai
Requires-Dist: boto3
Requires-Dist: dynaconf
Requires-Dist: toml
Requires-Dist: wove
Provides-Extra: recommended
Requires-Dist: llama-cpp-python; extra == "recommended"
Dynamic: author
Dynamic: author-email
Dynamic: classifier
Dynamic: description
Dynamic: description-content-type
Dynamic: home-page
Dynamic: license
Dynamic: license-file
Dynamic: provides-extra
Dynamic: requires-dist
Dynamic: requires-python
Dynamic: summary
